[
  {
    "url": "https://www.stordahl.dev/",
    "time_stamp": "2023-01-20T00:11:59.253Z",
    "first_contentful_paint": {
      "id": "first-contentful-paint",
      "title": "First Contentful Paint",
      "description": "First Contentful Paint marks the time at which the first text or image is painted. [Learn more](https://web.dev/first-contentful-paint/).",
      "score": 0.83,
      "scoreDisplayMode": "numeric",
      "numericValue": 2044.951,
      "numericUnit": "millisecond",
      "displayValue": "2.0 s"
    },
    "largest_contentful_paint": {
      "id": "largest-contentful-paint",
      "title": "Largest Contentful Paint",
      "description": "Largest Contentful Paint marks the time at which the largest text or image is painted. [Learn more](https://web.dev/lighthouse-largest-contentful-paint/)",
      "score": 0.97,
      "scoreDisplayMode": "numeric",
      "numericValue": 2044.951,
      "numericUnit": "millisecond",
      "displayValue": "2.0 s"
    },
    "first_meaningful_paint": {
      "id": "first-meaningful-paint",
      "title": "First Meaningful Paint",
      "description": "First Meaningful Paint measures when the primary content of a page is visible. [Learn more](https://web.dev/first-meaningful-paint/).",
      "score": 0.95,
      "scoreDisplayMode": "numeric",
      "numericValue": 2044.951,
      "numericUnit": "millisecond",
      "displayValue": "2.0 s"
    },
    "total_blocking_time": {
      "id": "total-blocking-time",
      "title": "Total Blocking Time",
      "description": "Sum of all time periods between FCP and Time to Interactive, when task length exceeded 50ms, expressed in milliseconds. [Learn more](https://web.dev/lighthouse-total-blocking-time/).",
      "score": 1,
      "scoreDisplayMode": "numeric",
      "numericValue": 19.5,
      "numericUnit": "millisecond",
      "displayValue": "20 ms"
    },
    "cumulative_layout_shift": {
      "id": "cumulative-layout-shift",
      "title": "Cumulative Layout Shift",
      "description": "Cumulative Layout Shift measures the movement of visible elements within the viewport. [Learn more](https://web.dev/cls/).",
      "score": 1,
      "scoreDisplayMode": "numeric",
      "numericValue": 0,
      "numericUnit": "unitless",
      "displayValue": "0",
      "details": {
        "type": "debugdata",
        "items": [
          {
            "cumulativeLayoutShiftMainFrame": 0,
            "totalCumulativeLayoutShift": 0
          }
        ]
      }
    },
    "speed_index": {
      "id": "speed-index",
      "title": "Speed Index",
      "description": "Speed Index shows how quickly the contents of a page are visibly populated. [Learn more](https://web.dev/speed-index/).",
      "score": 0.9,
      "scoreDisplayMode": "numeric",
      "numericValue": 3390.6539521285313,
      "numericUnit": "millisecond",
      "displayValue": "3.4 s"
    },
    "time_to_interactive": {
      "id": "interactive",
      "title": "Time to Interactive",
      "description": "Time to interactive is the amount of time it takes for the page to become fully interactive. [Learn more](https://web.dev/interactive/).",
      "score": 0.99,
      "scoreDisplayMode": "numeric",
      "numericValue": 2209.0205,
      "numericUnit": "millisecond",
      "displayValue": "2.2 s"
    },
    "metrics": [
      {
        "firstContentfulPaint": 2045,
        "firstMeaningfulPaint": 2045,
        "largestContentfulPaint": 2045,
        "interactive": 2209,
        "speedIndex": 3391,
        "totalBlockingTime": 20,
        "maxPotentialFID": 89,
        "cumulativeLayoutShift": 0,
        "cumulativeLayoutShiftMainFrame": 0,
        "totalCumulativeLayoutShift": 0,
        "observedTimeOrigin": 0,
        "observedTimeOriginTs": 66702571,
        "observedNavigationStart": 0,
        "observedNavigationStartTs": 66702571,
        "observedFirstPaint": 1566,
        "observedFirstPaintTs": 68268111,
        "observedFirstContentfulPaint": 1566,
        "observedFirstContentfulPaintTs": 68268111,
        "observedFirstContentfulPaintAllFrames": 1566,
        "observedFirstContentfulPaintAllFramesTs": 68268111,
        "observedFirstMeaningfulPaint": 1566,
        "observedFirstMeaningfulPaintTs": 68268111,
        "observedLargestContentfulPaint": 1566,
        "observedLargestContentfulPaintTs": 68268111,
        "observedLargestContentfulPaintAllFrames": 1566,
        "observedLargestContentfulPaintAllFramesTs": 68268111,
        "observedTraceEnd": 4005,
        "observedTraceEndTs": 70707076,
        "observedLoad": 1573,
        "observedLoadTs": 68276059,
        "observedDomContentLoaded": 1573,
        "observedDomContentLoadedTs": 68275964,
        "observedCumulativeLayoutShift": 0,
        "observedCumulativeLayoutShiftMainFrame": 0,
        "observedTotalCumulativeLayoutShift": 0,
        "observedFirstVisualChange": 1578,
        "observedFirstVisualChangeTs": 68280571,
        "observedLastVisualChange": 2161,
        "observedLastVisualChangeTs": 68863571,
        "observedSpeedIndex": 1590,
        "observedSpeedIndexTs": 68292268
      },
      {
        "lcpInvalidated": false
      }
    ]
  },
  {
    "url": "https://www.stordahl.dev/writing",
    "time_stamp": "2023-01-20T00:12:10.907Z",
    "first_contentful_paint": {
      "id": "first-contentful-paint",
      "title": "First Contentful Paint",
      "description": "First Contentful Paint marks the time at which the first text or image is painted. [Learn more](https://web.dev/first-contentful-paint/).",
      "score": 0.85,
      "scoreDisplayMode": "numeric",
      "numericValue": 1986.02,
      "numericUnit": "millisecond",
      "displayValue": "2.0 s"
    },
    "largest_contentful_paint": {
      "id": "largest-contentful-paint",
      "title": "Largest Contentful Paint",
      "description": "Largest Contentful Paint marks the time at which the largest text or image is painted. [Learn more](https://web.dev/lighthouse-largest-contentful-paint/)",
      "score": 0.97,
      "scoreDisplayMode": "numeric",
      "numericValue": 1986.02,
      "numericUnit": "millisecond",
      "displayValue": "2.0 s"
    },
    "first_meaningful_paint": {
      "id": "first-meaningful-paint",
      "title": "First Meaningful Paint",
      "description": "First Meaningful Paint measures when the primary content of a page is visible. [Learn more](https://web.dev/first-meaningful-paint/).",
      "score": 0.95,
      "scoreDisplayMode": "numeric",
      "numericValue": 1986.02,
      "numericUnit": "millisecond",
      "displayValue": "2.0 s"
    },
    "total_blocking_time": {
      "id": "total-blocking-time",
      "title": "Total Blocking Time",
      "description": "Sum of all time periods between FCP and Time to Interactive, when task length exceeded 50ms, expressed in milliseconds. [Learn more](https://web.dev/lighthouse-total-blocking-time/).",
      "score": 1,
      "scoreDisplayMode": "numeric",
      "numericValue": 0,
      "numericUnit": "millisecond",
      "displayValue": "0 ms"
    },
    "cumulative_layout_shift": {
      "id": "cumulative-layout-shift",
      "title": "Cumulative Layout Shift",
      "description": "Cumulative Layout Shift measures the movement of visible elements within the viewport. [Learn more](https://web.dev/cls/).",
      "score": 1,
      "scoreDisplayMode": "numeric",
      "numericValue": 0,
      "numericUnit": "unitless",
      "displayValue": "0",
      "details": {
        "type": "debugdata",
        "items": [
          {
            "cumulativeLayoutShiftMainFrame": 0,
            "totalCumulativeLayoutShift": 0
          }
        ]
      }
    },
    "speed_index": {
      "id": "speed-index",
      "title": "Speed Index",
      "description": "Speed Index shows how quickly the contents of a page are visibly populated. [Learn more](https://web.dev/speed-index/).",
      "score": 0.99,
      "scoreDisplayMode": "numeric",
      "numericValue": 1986.02,
      "numericUnit": "millisecond",
      "displayValue": "2.0 s"
    },
    "time_to_interactive": {
      "id": "interactive",
      "title": "Time to Interactive",
      "description": "Time to interactive is the amount of time it takes for the page to become fully interactive. [Learn more](https://web.dev/interactive/).",
      "score": 0.99,
      "scoreDisplayMode": "numeric",
      "numericValue": 1986.02,
      "numericUnit": "millisecond",
      "displayValue": "2.0 s"
    },
    "metrics": [
      {
        "firstContentfulPaint": 1986,
        "firstMeaningfulPaint": 1986,
        "largestContentfulPaint": 1986,
        "interactive": 1986,
        "speedIndex": 1986,
        "totalBlockingTime": 0,
        "maxPotentialFID": 46,
        "cumulativeLayoutShift": 0,
        "cumulativeLayoutShiftMainFrame": 0,
        "totalCumulativeLayoutShift": 0,
        "observedTimeOrigin": 0,
        "observedTimeOriginTs": 78305362,
        "observedNavigationStart": 0,
        "observedNavigationStartTs": 78305362,
        "observedFirstPaint": 312,
        "observedFirstPaintTs": 78617013,
        "observedFirstContentfulPaint": 312,
        "observedFirstContentfulPaintTs": 78617013,
        "observedFirstContentfulPaintAllFrames": 312,
        "observedFirstContentfulPaintAllFramesTs": 78617013,
        "observedFirstMeaningfulPaint": 312,
        "observedFirstMeaningfulPaintTs": 78617013,
        "observedLargestContentfulPaint": 312,
        "observedLargestContentfulPaintTs": 78617013,
        "observedLargestContentfulPaintAllFrames": 312,
        "observedLargestContentfulPaintAllFramesTs": 78617013,
        "observedTraceEnd": 2715,
        "observedTraceEndTs": 81020509,
        "observedLoad": 311,
        "observedLoadTs": 78616498,
        "observedDomContentLoaded": 311,
        "observedDomContentLoadedTs": 78616391,
        "observedCumulativeLayoutShift": 0,
        "observedCumulativeLayoutShiftMainFrame": 0,
        "observedTotalCumulativeLayoutShift": 0,
        "observedFirstVisualChange": 324,
        "observedFirstVisualChangeTs": 78629362,
        "observedLastVisualChange": 908,
        "observedLastVisualChangeTs": 79213362,
        "observedSpeedIndex": 331,
        "observedSpeedIndexTs": 78636021
      },
      {
        "lcpInvalidated": false
      }
    ]
  }
]